[
  {
    "id": 90022,
    "islandGuideId": 1,
    "name": "Banana Reef",
    "slug": "banana-reef-thulusdhoo",
    "spotType": "dive_site",
    "description": "Iconic banana-shaped reef with excellent coral formations and abundant fish life. Perfect for beginners and intermediate divers.",
    "difficulty": "beginner",
    "latitude": "4.2333",
    "longitude": "73.2667",
    "accessInfo": null,
    "bestSeason": "March to October",
    "bestTime": "Morning (6am-10am)",
    "waterConditions": null,
    "maxDepth": 30,
    "minDepth": 5,
    "marineLife": "Grouper, snapper, trevally, reef sharks",
    "waveHeight": null,
    "waveType": null,
    "coralCoverage": "95% hard coral",
    "fishSpecies": null,
    "tips": null,
    "facilities": null,
    "images": null,
    "metaTitle": null,
    "metaDescription": null,
    "published": 1,
    "featured": 0,
    "displayOrder": 0,
    "viewCount": 0,
    "createdAt": "2026-02-12T12:37:58.000Z",
    "updatedAt": "2026-03-16T07:35:10.000Z",
    "atollId": null,
    "category": null,
    "rating": "4.5",
    "reviewCount": 0,
    "capacity": null,
    "operatorInfo": null,
    "primaryTypeId": null,
    "placeId": null
  },
  {
    "id": 90004,
    "islandGuideId": 1,
    "name": "Chickens",
    "slug": "chickens-thulusdhoo",
    "spotType": "surf_spot",
    "description": "Mellow right-hand reef break. Forgiving waves with plenty of shoulder. Ideal for learning and progression.",
    "difficulty": "beginner",
    "latitude": "4.2320",
    "longitude": "73.2700",
    "accessInfo": null,
    "bestSeason": "March to October",
    "bestTime": "Morning (7am-12pm)",
    "waterConditions": null,
    "maxDepth": 12,
    "minDepth": 2,
    "marineLife": "Small reef fish",
    "waveHeight": "2-4 feet",
    "waveType": null,
    "coralCoverage": "Light coral",
    "fishSpecies": null,
    "tips": null,
    "facilities": null,
    "images": null,
    "metaTitle": null,
    "metaDescription": null,
    "published": 1,
    "featured": 0,
    "displayOrder": 0,
    "viewCount": 0,
    "createdAt": "2026-02-12T12:34:19.000Z",
    "updatedAt": "2026-02-14T10:46:19.000Z",
    "atollId": null,
    "category": null,
    "rating": null,
    "reviewCount": 0,
    "capacity": null,
    "operatorInfo": null,
    "primaryTypeId": null,
    "placeId": null
  },
  {
    "id": 90001,
    "islandGuideId": 1,
    "name": "Cokes",
    "slug": "cokes-thulusdhoo",
    "spotType": "surf_spot",
    "description": "Fast right-hand reef break with consistent waves. Perfect for beginners and intermediate surfers. Mellow and forgiving.",
    "difficulty": "beginner",
    "latitude": "4.2333",
    "longitude": "73.2667",
    "accessInfo": null,
    "bestSeason": "March to October",
    "bestTime": "Morning (6am-10am)",
    "waterConditions": null,
    "maxDepth": 15,
    "minDepth": 2,
    "marineLife": "Reef fish, occasional turtles",
    "waveHeight": "2-4 feet",
    "waveType": null,
    "coralCoverage": "Heavy coral - reef break",
    "fishSpecies": null,
    "tips": null,
    "facilities": null,
    "images": null,
    "metaTitle": null,
    "metaDescription": null,
    "published": 1,
    "featured": 0,
    "displayOrder": 0,
    "viewCount": 0,
    "createdAt": "2026-02-12T12:34:19.000Z",
    "updatedAt": "2026-02-14T10:46:19.000Z",
    "atollId": null,
    "category": null,
    "rating": null,
    "reviewCount": 0,
    "capacity": null,
    "operatorInfo": null,
    "primaryTypeId": null,
    "placeId": null
  },
  {
    "id": 90003,
    "islandGuideId": 1,
    "name": "Jails",
    "slug": "jails-thulusdhoo",
    "spotType": "surf_spot",
    "description": "Powerful right-hand reef break with hollow sections. Requires experience and good paddling fitness. Heavy water movement.",
    "difficulty": "advanced",
    "latitude": "4.2300",
    "longitude": "73.2650",
    "accessInfo": null,
    "bestSeason": "March to October",
    "bestTime": "Morning (6am-11am)",
    "waterConditions": null,
    "maxDepth": 25,
    "minDepth": 4,
    "marineLife": "Reef sharks, barracuda",
    "waveHeight": "4-6 feet",
    "waveType": null,
    "coralCoverage": "Heavy coral - sharp reef",
    "fishSpecies": null,
    "tips": null,
    "facilities": null,
    "images": null,
    "metaTitle": null,
    "metaDescription": null,
    "published": 1,
    "featured": 0,
    "displayOrder": 0,
    "viewCount": 0,
    "createdAt": "2026-02-12T12:34:19.000Z",
    "updatedAt": "2026-02-14T10:46:19.000Z",
    "atollId": null,
    "category": null,
    "rating": null,
    "reviewCount": 0,
    "capacity": null,
    "operatorInfo": null,
    "primaryTypeId": null,
    "placeId": null
  },
  {
    "id": 90023,
    "islandGuideId": 1,
    "name": "Miyaru Kandu",
    "slug": "miyaru-kandu-thulusdhoo",
    "spotType": "dive_site",
    "description": "A fast-paced drift dive known for reliable sightings of grey reef sharks, whitetips, tuna, and schooling barracuda. Strong currents and excellent visibility make it a favorite for experienced divers chasing big action and pelagic encounters.",
    "difficulty": "advanced",
    "latitude": "4.2350",
    "longitude": "73.2680",
    "accessInfo": null,
    "bestSeason": "January-April",
    "bestTime": "Morning (6am-9am)",
    "waterConditions": null,
    "maxDepth": 35,
    "minDepth": 5,
    "marineLife": "[\"Grey reef sharks\", \"White-tip sharks\", \"Tuna\", \"Barracuda schools\", \"Jacks\"]",
    "waveHeight": null,
    "waveType": null,
    "coralCoverage": "80% coral",
    "fishSpecies": null,
    "tips": null,
    "facilities": null,
    "images": null,
    "metaTitle": null,
    "metaDescription": null,
    "published": 1,
    "featured": 0,
    "displayOrder": 0,
    "viewCount": 0,
    "createdAt": "2026-02-12T12:37:58.000Z",
    "updatedAt": "2026-03-16T07:34:35.000Z",
    "atollId": null,
    "category": null,
    "rating": "4.7",
    "reviewCount": 0,
    "capacity": null,
    "operatorInfo": null,
    "primaryTypeId": null,
    "placeId": null
  },
  {
    "id": 90002,
    "islandGuideId": 1,
    "name": "Pasta Point",
    "slug": "pasta-point-thulusdhoo",
    "spotType": "surf_spot",
    "description": "Excellent left-hand reef break with long, peeling waves. Named after the Italian restaurant nearby. Great for intermediate surfers.",
    "difficulty": "intermediate",
    "latitude": "4.2350",
    "longitude": "73.2680",
    "accessInfo": null,
    "bestSeason": "March to October",
    "bestTime": "Early morning (5am-9am)",
    "waterConditions": null,
    "maxDepth": 20,
    "minDepth": 3,
    "marineLife": "Reef sharks, trevally, grouper",
    "waveHeight": "3-5 feet",
    "waveType": null,
    "coralCoverage": "Moderate coral",
    "fishSpecies": null,
    "tips": null,
    "facilities": null,
    "images": null,
    "metaTitle": null,
    "metaDescription": null,
    "published": 1,
    "featured": 0,
    "displayOrder": 0,
    "viewCount": 0,
    "createdAt": "2026-02-12T12:34:19.000Z",
    "updatedAt": "2026-02-14T10:46:19.000Z",
    "atollId": null,
    "category": null,
    "rating": null,
    "reviewCount": 0,
    "capacity": null,
    "operatorInfo": null,
    "primaryTypeId": null,
    "placeId": null
  },
  {
    "id": 90054,
    "islandGuideId": 1,
    "name": "Thulusdhoo House Reef",
    "slug": "thulusdhoo-house-reef",
    "spotType": "snorkeling_spot",
    "description": "Beautiful house reef with vibrant coral and tropical fish, perfect for beginners. Excellent for first-time snorkelers.",
    "difficulty": "beginner",
    "latitude": "4.374369",
    "longitude": "73.651413",
    "accessInfo": null,
    "bestSeason": "Year-round",
    "bestTime": "8am-4pm",
    "waterConditions": null,
    "maxDepth": 5,
    "minDepth": 0,
    "marineLife": "Tropical fish, clownfish, parrotfish, damselfish",
    "waveHeight": null,
    "waveType": null,
    "coralCoverage": "85%",
    "fishSpecies": "Clownfish, Parrotfish, Damselfish, Angelfish",
    "tips": null,
    "facilities": null,
    "images": null,
    "metaTitle": null,
    "metaDescription": null,
    "published": 1,
    "featured": 0,
    "displayOrder": 0,
    "viewCount": 0,
    "createdAt": "2026-02-12T12:58:42.000Z",
    "updatedAt": "2026-02-14T10:46:19.000Z",
    "atollId": null,
    "category": null,
    "rating": null,
    "reviewCount": 0,
    "capacity": null,
    "operatorInfo": null,
    "primaryTypeId": null,
    "placeId": null
  },
  {
    "id": 60010,
    "islandGuideId": 60003,
    "name": "Thulusdhoo Reef",
    "slug": "thulusdhoo-reef",
    "spotType": "snorkeling_spot",
    "description": "Shallow reef perfect for beginners",
    "difficulty": "beginner",
    "latitude": "4.33",
    "longitude": "73.56",
    "accessInfo": null,
    "bestSeason": "All Year",
    "bestTime": null,
    "waterConditions": null,
    "maxDepth": null,
    "minDepth": null,
    "marineLife": null,
    "waveHeight": null,
    "waveType": null,
    "coralCoverage": null,
    "fishSpecies": null,
    "tips": null,
    "facilities": null,
    "images": null,
    "metaTitle": null,
    "metaDescription": null,
    "published": 1,
    "featured": 0,
    "displayOrder": 0,
    "viewCount": 0,
    "createdAt": "2026-02-11T20:44:37.000Z",
    "updatedAt": "2026-02-14T10:46:19.000Z",
    "atollId": null,
    "category": null,
    "rating": null,
    "reviewCount": 0,
    "capacity": null,
    "operatorInfo": null,
    "primaryTypeId": null,
    "placeId": null
  }
]